{"nodes": [{"id": "app_robots_robots", "label": "robots() Route Handler", "file_type": "code", "source_file": "app/robots.ts", "source_location": "4", "source_url": null, "captured_at": null, "author": null, "contributor": null}], "edges": [{"source": "concept_static_export", "target": "app_robots_robots", "relation": "conceptually_related_to", "confidence": "INFERRED", "confidence_score": 0.85, "source_file": "app/robots.ts", "source_location": "1", "weight": 0.8}, {"source": "app_robots_robots", "target": "app_sitemap_sitemap", "relation": "references", "confidence": "EXTRACTED", "confidence_score": 1.0, "source_file": "app/robots.ts", "source_location": "7", "weight": 1.0}], "hyperedges": []}